scoda/__init__.py
scoda/cpdb.py
scoda/deiso.py
scoda/icnv.py
scoda/misc.py
scoda_tk-0.6.6.dist-info/LICENSE
scoda_tk-0.6.6.dist-info/METADATA
scoda_tk-0.6.6.dist-info/WHEEL
scoda_tk-0.6.6.dist-info/entry_points.txt
scoda_tk-0.6.6.dist-info/top_level.txt
scoda_tk-0.6.6.dist-info/RECORD
