Metadata-Version: 2.1
Name: scoda-tk
Version: 0.6.6
Summary: Toolkits for single-cell omics data analysis. (including wrapper functions for CellPhoneDB, GSEApy and InferCNVpy)
Author-email: Seokhyun Yoon <syoon@dku.edu>
License: GNU GENERAL PUBLIC LICENSE
Project-URL: Homepage, https://github.com/combio-dku
Keywords: single-cell omics,bioinformatics
Classifier: Programming Language :: Python
Classifier: Programming Language :: Python :: 3
License-File: LICENSE
Provides-Extra: dev
Requires-Dist: numpy ; extra == 'dev'
Requires-Dist: pandas ; extra == 'dev'
Requires-Dist: scipy ; extra == 'dev'
Requires-Dist: scikit-learn ; extra == 'dev'
Requires-Dist: scikit-network ; extra == 'dev'
